movshon_lab_to_nwb/__init__.py
movshon_lab_to_nwb/cmd_line.py
movshon_lab_to_nwb/expodatainterface.py
movshon_lab_to_nwb/movshonnwbconverter.py
movshon_lab_to_nwb/utils_expo.py
movshon_lab_to_nwb-0.1.1.dist-info/LICENSE
movshon_lab_to_nwb-0.1.1.dist-info/METADATA
movshon_lab_to_nwb-0.1.1.dist-info/WHEEL
movshon_lab_to_nwb-0.1.1.dist-info/entry_points.txt
movshon_lab_to_nwb-0.1.1.dist-info/top_level.txt
movshon_lab_to_nwb-0.1.1.dist-info/RECORD
