Metadata-Version: 2.1
Name: movshon-lab-to-nwb
Version: 0.1.1
Summary: NWB conversion scripts and tutorials.
Home-page: https://github.com/catalystneuro/movshon-lab-to-nwb
Author: Luiz Tauffer and Ben Dichter
Author-email: ben.dichter@gmail.com
License: UNKNOWN
Platform: UNKNOWN
License-File: LICENSE
Requires-Dist: notebook
Requires-Dist: pynwb
Requires-Dist: h5py
Requires-Dist: pyopenephys
Requires-Dist: neo
Requires-Dist: spikeextractors
Requires-Dist: spiketoolkit
Requires-Dist: spikesorters
Requires-Dist: spikecomparison
Requires-Dist: spikewidgets
Requires-Dist: klusta
Requires-Dist: klustakwik2
Requires-Dist: herdingspikes
Requires-Dist: nwb-conversion-tools
Requires-Dist: nwb-web-gui
